{
  "id": "7:3650",
  "name": "explorer",
  "type": "FRAME",
  "scrollBehavior": "SCROLLS",
  "children": [
    {
      "id": "7:3649",
      "name": "Container",
      "type": "FRAME",
      "scrollBehavior": "SCROLLS",
      "children": [
        {
          "id": "7:3139",
          "name": "Paragraph_container",
          "type": "FRAME",
          "scrollBehavior": "SCROLLS",
          "children": [
            {
              "id": "1:1327",
              "name": "Explore",
              "type": "TEXT",
              "scrollBehavior": "SCROLLS",
              "boundVariables": {
                "fills": [
                  {
                    "type": "VARIABLE_ALIAS",
                    "id": "VariableID:d3b21d78537196b16a3dc7bb68c6128b57fce7e0/732:4"
                  }
                ]
              },
              "blendMode": "PASS_THROUGH",
              "fills": [
                {
                  "blendMode": "NORMAL",
                  "type": "SOLID",
                  "color": {
                    "r": 0.25882354378700256,
                    "g": 0.25882354378700256,
                    "b": 0.25882354378700256,
                    "a": 1
                  },
                  "boundVariables": {
                    "color": {
                      "type": "VARIABLE_ALIAS",
                      "id": "VariableID:d3b21d78537196b16a3dc7bb68c6128b57fce7e0/732:4"
                    }
                  }
                }
              ],
              "strokes": [],
              "strokeWeight": 1,
              "strokeAlign": "OUTSIDE",
              "absoluteBoundingBox": {
                "x": -2853,
                "y": 390.8571472167969,
                "width": 1180,
                "height": 32
              },
              "absoluteRenderBounds": {
                "x": -2850.890625,
                "y": 395.2321472167969,
                "width": 107.765625,
                "height": 29
              },
              "constraints": {
                "vertical": "TOP",
                "horizontal": "LEFT"
              },
              "layoutAlign": "STRETCH",
              "layoutGrow": 0,
              "layoutSizingHorizontal": "FILL",
              "layoutSizingVertical": "HUG",
              "characters": "Explore",
              "characterStyleOverrides": [],
              "styleOverrideTable": {},
              "lineTypes": [
                "NONE"
              ],
              "lineIndentations": [
                0
              ],
              "style": {
                "fontFamily": "Pretendard Variable",
                "fontPostScriptName": "PretendardVariable-SemiBold",
                "fontStyle": "SemiBold",
                "fontWeight": 600,
                "textAutoResize": "HEIGHT",
                "fontSize": 32,
                "textAlignHorizontal": "LEFT",
                "textAlignVertical": "TOP",
                "letterSpacing": 0,
                "lineHeightPx": 32,
                "lineHeightPercent": 83.79705047607422,
                "lineHeightPercentFontSize": 100,
                "lineHeightUnit": "FONT_SIZE_%"
              },
              "layoutVersion": 4,
              "effects": [],
              "interactions": []
            },
            {
              "id": "1:1375",
              "name": "More to see",
              "type": "TEXT",
              "scrollBehavior": "SCROLLS",
              "boundVariables": {
                "fills": [
                  {
                    "type": "VARIABLE_ALIAS",
                    "id": "VariableID:c2710e6f0ac0518945ad8735be66e48aabf2536f/732:15"
                  }
                ]
              },
              "blendMode": "PASS_THROUGH",
              "fills": [
                {
                  "blendMode": "NORMAL",
                  "type": "SOLID",
                  "color": {
                    "r": 0,
                    "g": 0,
                    "b": 0,
                    "a": 1
                  },
                  "boundVariables": {
                    "color": {
                      "type": "VARIABLE_ALIAS",
                      "id": "VariableID:c2710e6f0ac0518945ad8735be66e48aabf2536f/732:15"
                    }
                  }
                }
              ],
              "strokes": [],
              "strokeWeight": 1,
              "strokeAlign": "OUTSIDE",
              "absoluteBoundingBox": {
                "x": -2853,
                "y": 450.8571472167969,
                "width": 1180,
                "height": 48
              },
              "absoluteRenderBounds": {
                "x": -2850.4921875,
                "y": 453.4665222167969,
                "width": 340.2421875,
                "height": 42.8203125
              },
              "constraints": {
                "vertical": "TOP",
                "horizontal": "LEFT"
              },
              "layoutAlign": "STRETCH",
              "layoutGrow": 0,
              "layoutSizingHorizontal": "FILL",
              "layoutSizingVertical": "HUG",
              "characters": "이미지만 모아보다",
              "characterStyleOverrides": [],
              "styleOverrideTable": {},
              "lineTypes": [
                "NONE"
              ],
              "lineIndentations": [
                0
              ],
              "style": {
                "fontFamily": "Pretendard Variable",
                "fontPostScriptName": "PretendardVariable-Bold",
                "fontStyle": "Bold",
                "fontWeight": 700,
                "textAutoResize": "HEIGHT",
                "fontSize": 48,
                "textAlignHorizontal": "LEFT",
                "textAlignVertical": "TOP",
                "letterSpacing": 0,
                "lineHeightPx": 48,
                "lineHeightPercent": 83.79705047607422,
                "lineHeightPercentFontSize": 100,
                "lineHeightUnit": "FONT_SIZE_%"
              },
              "layoutVersion": 4,
              "effects": [],
              "interactions": []
            }
          ],
          "blendMode": "PASS_THROUGH",
          "clipsContent": false,
          "background": [],
          "fills": [],
          "strokes": [],
          "strokeWeight": 1,
          "strokeAlign": "INSIDE",
          "backgroundColor": {
            "r": 0,
            "g": 0,
            "b": 0,
            "a": 0
          },
          "layoutMode": "VERTICAL",
          "counterAxisSizingMode": "FIXED",
          "itemSpacing": 28,
          "layoutWrap": "NO_WRAP",
          "absoluteBoundingBox": {
            "x": -2853,
            "y": 390.8571472167969,
            "width": 1180,
            "height": 108
          },
          "absoluteRenderBounds": {
            "x": -2853,
            "y": 390.8571472167969,
            "width": 1180,
            "height": 108
          },
          "constraints": {
            "vertical": "TOP",
            "horizontal": "LEFT"
          },
          "layoutAlign": "STRETCH",
          "layoutGrow": 0,
          "layoutSizingHorizontal": "FILL",
          "layoutSizingVertical": "HUG",
          "effects": [],
          "interactions": []
        },
        {
          "id": "1:1374",
          "name": "category",
          "type": "INSTANCE",
          "scrollBehavior": "SCROLLS",
          "componentId": "1:1295",
          "componentProperties": {
            "Property 1": {
              "value": "Default",
              "type": "VARIANT",
              "boundVariables": {}
            }
          },
          "overrides": [
            {
              "id": "1:1374",
              "overriddenFields": [
                "counterAxisAlignItems",
                "height",
                "name",
                "primaryAxisAlignItems",
                "width"
              ]
            },
            {
              "id": "I1:1374;812:6747",
              "overriddenFields": [
                "lineHeightPercent",
                "lineHeightPercentFontSize",
                "lineHeightPx",
                "lineHeightUnit"
              ]
            },
            {
              "id": "I1:1374;812:6748",
              "overriddenFields": [
                "lineHeightPercent",
                "lineHeightPercentFontSize",
                "lineHeightPx",
                "lineHeightUnit"
              ]
            },
            {
              "id": "I1:1374;812:6749",
              "overriddenFields": [
                "lineHeightPercent",
                "lineHeightPercentFontSize",
                "lineHeightPx",
                "lineHeightUnit"
              ]
            },
            {
              "id": "I1:1374;817:2723",
              "overriddenFields": [
                "lineHeightPercent",
                "lineHeightPercentFontSize",
                "lineHeightPx",
                "lineHeightUnit"
              ]
            }
          ],
          "children": [
            {
              "id": "I1:1374;812:6747",
              "name": "Random",
              "type": "TEXT",
              "scrollBehavior": "SCROLLS",
              "boundVariables": {
                "fills": [
                  {
                    "type": "VARIABLE_ALIAS",
                    "id": "VariableID:18a8c232873d4aeaa37cfbbf56e3d76f89cb3f9f/732:2"
                  }
                ]
              },
              "blendMode": "PASS_THROUGH",
              "fills": [
                {
                  "blendMode": "NORMAL",
                  "type": "SOLID",
                  "color": {
                    "r": 0.5568627715110779,
                    "g": 0.5568627715110779,
                    "b": 0.5764706134796143,
                    "a": 1
                  },
                  "boundVariables": {
                    "color": {
                      "type": "VARIABLE_ALIAS",
                      "id": "VariableID:18a8c232873d4aeaa37cfbbf56e3d76f89cb3f9f/732:2"
                    }
                  }
                }
              ],
              "strokes": [],
              "strokeWeight": 1,
              "strokeAlign": "OUTSIDE",
              "absoluteBoundingBox": {
                "x": -2853,
                "y": 540.857177734375,
                "width": 92,
                "height": 36
              },
              "absoluteRenderBounds": {
                "x": -2851.417236328125,
                "y": 550.8848266601562,
                "width": 88.4072265625,
                "height": 17.229248046875
              },
              "constraints": {
                "vertical": "TOP",
                "horizontal": "LEFT"
              },
              "layoutAlign": "INHERIT",
              "layoutGrow": 0,
              "layoutSizingHorizontal": "HUG",
              "layoutSizingVertical": "HUG",
              "characters": "Random",
              "characterStyleOverrides": [],
              "styleOverrideTable": {},
              "lineTypes": [
                "NONE"
              ],
              "lineIndentations": [
                0
              ],
              "style": {
                "fontFamily": "Pretendard Variable",
                "fontPostScriptName": "PretendardVariable-SemiBold",
                "fontStyle": "SemiBold",
                "fontWeight": 600,
                "textAutoResize": "WIDTH_AND_HEIGHT",
                "fontSize": 24,
                "textAlignHorizontal": "LEFT",
                "textAlignVertical": "TOP",
                "letterSpacing": 0,
                "lineHeightPx": 36,
                "lineHeightPercent": 125.00719451904297,
                "lineHeightPercentFontSize": 150,
                "lineHeightUnit": "FONT_SIZE_%"
              },
              "layoutVersion": 4,
              "effects": [],
              "transitionNodeID": "1:1310",
              "transitionDuration": 300,
              "transitionEasing": "EASE_OUT",
              "interactions": [
                {
                  "trigger": {
                    "type": "ON_CLICK"
                  },
                  "actions": [
                    {
                      "type": "NODE",
                      "destinationId": "1:1310",
                      "navigation": "CHANGE_TO",
                      "transition": {
                        "type": "DISSOLVE",
                        "easing": {
                          "type": "EASE_OUT"
                        },
                        "duration": 0.30000001192092896
                      },
                      "resetVideoPosition": false
                    }
                  ]
                }
              ]
            },
            {
              "id": "I1:1374;812:6748",
              "name": "New",
              "type": "TEXT",
              "scrollBehavior": "SCROLLS",
              "boundVariables": {
                "fills": [
                  {
                    "type": "VARIABLE_ALIAS",
                    "id": "VariableID:18a8c232873d4aeaa37cfbbf56e3d76f89cb3f9f/732:2"
                  }
                ]
              },
              "blendMode": "PASS_THROUGH",
              "fills": [
                {
                  "blendMode": "NORMAL",
                  "type": "SOLID",
                  "color": {
                    "r": 0.5568627715110779,
                    "g": 0.5568627715110779,
                    "b": 0.5764706134796143,
                    "a": 1
                  },
                  "boundVariables": {
                    "color": {
                      "type": "VARIABLE_ALIAS",
                      "id": "VariableID:18a8c232873d4aeaa37cfbbf56e3d76f89cb3f9f/732:2"
                    }
                  }
                }
              ],
              "strokes": [],
              "strokeWeight": 1,
              "strokeAlign": "OUTSIDE",
              "absoluteBoundingBox": {
                "x": -2741,
                "y": 540.857177734375,
                "width": 50,
                "height": 36
              },
              "absoluteRenderBounds": {
                "x": -2739.417236328125,
                "y": 550.8848266601562,
                "width": 47.903564453125,
                "height": 17.220947265625
              },
              "constraints": {
                "vertical": "TOP",
                "horizontal": "LEFT"
              },
              "layoutAlign": "INHERIT",
              "layoutGrow": 0,
              "layoutSizingHorizontal": "HUG",
              "layoutSizingVertical": "HUG",
              "characters": "New",
              "characterStyleOverrides": [],
              "styleOverrideTable": {},
              "lineTypes": [
                "NONE"
              ],
              "lineIndentations": [
                0
              ],
              "style": {
                "fontFamily": "Pretendard Variable",
                "fontPostScriptName": "PretendardVariable-SemiBold",
                "fontStyle": "SemiBold",
                "fontWeight": 600,
                "textAutoResize": "WIDTH_AND_HEIGHT",
                "fontSize": 24,
                "textAlignHorizontal": "LEFT",
                "textAlignVertical": "TOP",
                "letterSpacing": 0,
                "lineHeightPx": 36,
                "lineHeightPercent": 125.00719451904297,
                "lineHeightPercentFontSize": 150,
                "lineHeightUnit": "FONT_SIZE_%"
              },
              "layoutVersion": 4,
              "effects": [],
              "interactions": []
            },
            {
              "id": "I1:1374;812:6749",
              "name": "My Likes",
              "type": "TEXT",
              "scrollBehavior": "SCROLLS",
              "boundVariables": {
                "fills": [
                  {
                    "type": "VARIABLE_ALIAS",
                    "id": "VariableID:18a8c232873d4aeaa37cfbbf56e3d76f89cb3f9f/732:2"
                  }
                ]
              },
              "blendMode": "PASS_THROUGH",
              "fills": [
                {
                  "blendMode": "NORMAL",
                  "type": "SOLID",
                  "color": {
                    "r": 0.5568627715110779,
                    "g": 0.5568627715110779,
                    "b": 0.5764706134796143,
                    "a": 1
                  },
                  "boundVariables": {
                    "color": {
                      "type": "VARIABLE_ALIAS",
                      "id": "VariableID:18a8c232873d4aeaa37cfbbf56e3d76f89cb3f9f/732:2"
                    }
                  }
                }
              ],
              "strokes": [],
              "strokeWeight": 1,
              "strokeAlign": "OUTSIDE",
              "absoluteBoundingBox": {
                "x": -2671,
                "y": 540.857177734375,
                "width": 98,
                "height": 36
              },
              "absoluteRenderBounds": {
                "x": -2669.417236328125,
                "y": 550.0726318359375,
                "width": 94.995849609375,
                "height": 22.55804443359375
              },
              "constraints": {
                "vertical": "TOP",
                "horizontal": "LEFT"
              },
              "layoutAlign": "INHERIT",
              "layoutGrow": 0,
              "layoutSizingHorizontal": "HUG",
              "layoutSizingVertical": "HUG",
              "characters": "My Likes",
              "characterStyleOverrides": [],
              "styleOverrideTable": {},
              "lineTypes": [
                "NONE"
              ],
              "lineIndentations": [
                0
              ],
              "style": {
                "fontFamily": "Pretendard Variable",
                "fontPostScriptName": "PretendardVariable-SemiBold",
                "fontStyle": "SemiBold",
                "fontWeight": 600,
                "textAutoResize": "WIDTH_AND_HEIGHT",
                "fontSize": 24,
                "textAlignHorizontal": "LEFT",
                "textAlignVertical": "TOP",
                "letterSpacing": 0,
                "lineHeightPx": 36,
                "lineHeightPercent": 125.00719451904297,
                "lineHeightPercentFontSize": 150,
                "lineHeightUnit": "FONT_SIZE_%"
              },
              "layoutVersion": 4,
              "effects": [],
              "interactions": []
            },
            {
              "id": "I1:1374;817:2723",
              "name": "Cart",
              "type": "TEXT",
              "scrollBehavior": "SCROLLS",
              "boundVariables": {
                "fills": [
                  {
                    "type": "VARIABLE_ALIAS",
                    "id": "VariableID:18a8c232873d4aeaa37cfbbf56e3d76f89cb3f9f/732:2"
                  }
                ]
              },
              "blendMode": "PASS_THROUGH",
              "fills": [
                {
                  "blendMode": "NORMAL",
                  "type": "SOLID",
                  "color": {
                    "r": 0.5568627715110779,
                    "g": 0.5568627715110779,
                    "b": 0.5764706134796143,
                    "a": 1
                  },
                  "boundVariables": {
                    "color": {
                      "type": "VARIABLE_ALIAS",
                      "id": "VariableID:18a8c232873d4aeaa37cfbbf56e3d76f89cb3f9f/732:2"
                    }
                  }
                }
              ],
              "strokes": [],
              "strokeWeight": 1,
              "strokeAlign": "OUTSIDE",
              "absoluteBoundingBox": {
                "x": -2553,
                "y": 540.857177734375,
                "width": 49,
                "height": 36
              },
              "absoluteRenderBounds": {
                "x": -2551.8564453125,
                "y": 550.6527709960938,
                "width": 46.882080078125,
                "height": 17.4613037109375
              },
              "constraints": {
                "vertical": "TOP",
                "horizontal": "LEFT"
              },
              "layoutAlign": "INHERIT",
              "layoutGrow": 0,
              "layoutSizingHorizontal": "HUG",
              "layoutSizingVertical": "HUG",
              "characters": "Cart",
              "characterStyleOverrides": [],
              "styleOverrideTable": {},
              "lineTypes": [
                "NONE"
              ],
              "lineIndentations": [
                0
              ],
              "style": {
                "fontFamily": "Pretendard Variable",
                "fontPostScriptName": "PretendardVariable-SemiBold",
                "fontStyle": "SemiBold",
                "fontWeight": 600,
                "textAutoResize": "WIDTH_AND_HEIGHT",
                "fontSize": 24,
                "textAlignHorizontal": "LEFT",
                "textAlignVertical": "TOP",
                "letterSpacing": 0,
                "lineHeightPx": 36,
                "lineHeightPercent": 125.00719451904297,
                "lineHeightPercentFontSize": 150,
                "lineHeightUnit": "FONT_SIZE_%"
              },
              "layoutVersion": 4,
              "effects": [],
              "interactions": []
            }
          ],
          "blendMode": "PASS_THROUGH",
          "clipsContent": false,
          "background": [],
          "fills": [],
          "strokes": [],
          "strokeWeight": 1,
          "strokeAlign": "INSIDE",
          "backgroundColor": {
            "r": 0,
            "g": 0,
            "b": 0,
            "a": 0
          },
          "layoutMode": "HORIZONTAL",
          "counterAxisAlignItems": "CENTER",
          "itemSpacing": 20,
          "layoutWrap": "NO_WRAP",
          "absoluteBoundingBox": {
            "x": -2853,
            "y": 540.857177734375,
            "width": 349,
            "height": 36
          },
          "absoluteRenderBounds": {
            "x": -2853,
            "y": 540.857177734375,
            "width": 349,
            "height": 36
          },
          "constraints": {
            "vertical": "TOP",
            "horizontal": "LEFT"
          },
          "layoutAlign": "INHERIT",
          "layoutGrow": 0,
          "layoutSizingHorizontal": "HUG",
          "layoutSizingVertical": "HUG",
          "effects": [],
          "interactions": []
        }
      ],
      "blendMode": "PASS_THROUGH",
      "clipsContent": false,
      "background": [],
      "fills": [],
      "strokes": [],
      "strokeWeight": 1,
      "strokeAlign": "INSIDE",
      "backgroundColor": {
        "r": 0,
        "g": 0,
        "b": 0,
        "a": 0
      },
      "layoutMode": "VERTICAL",
      "counterAxisSizingMode": "FIXED",
      "itemSpacing": 42,
      "layoutWrap": "NO_WRAP",
      "absoluteBoundingBox": {
        "x": -2853,
        "y": 390.8571472167969,
        "width": 1180,
        "height": 186
      },
      "absoluteRenderBounds": {
        "x": -2853,
        "y": 390.8571472167969,
        "width": 1180,
        "height": 186.00003051757812
      },
      "constraints": {
        "vertical": "TOP",
        "horizontal": "LEFT"
      },
      "layoutAlign": "STRETCH",
      "layoutGrow": 0,
      "layoutSizingHorizontal": "FILL",
      "layoutSizingVertical": "HUG",
      "effects": [],
      "interactions": []
    },
    {
      "id": "7:3137",
      "name": "Container",
      "type": "FRAME",
      "scrollBehavior": "SCROLLS",
      "children": [
        {
          "id": "7:3136",
          "name": "Container",
          "type": "FRAME",
          "scrollBehavior": "SCROLLS",
          "children": [
            {
              "id": "7:3135",
              "name": "Card",
              "type": "FRAME",
              "scrollBehavior": "SCROLLS",
              "boundVariables": {
                "minWidth": {
                  "type": "VARIABLE_ALIAS",
                  "id": "VariableID:131:4121"
                },
                "maxWidth": {
                  "type": "VARIABLE_ALIAS",
                  "id": "VariableID:131:4122"
                }
              },
              "children": [
                {
                  "id": "1:1359",
                  "name": "Image_1",
                  "type": "RECTANGLE",
                  "scrollBehavior": "SCROLLS",
                  "blendMode": "PASS_THROUGH",
                  "fills": [
                    {
                      "blendMode": "NORMAL",
                      "type": "IMAGE",
                      "scaleMode": "FILL",
                      "imageRef": "561c3d1401323da520ec1d0c188dfbde9d9a3e38"
                    }
                  ],
                  "strokes": [],
                  "strokeWeight": 1,
                  "strokeAlign": "INSIDE",
                  "absoluteBoundingBox": {
                    "x": -2853,
                    "y": 624.857177734375,
                    "width": 380,
                    "height": 501.8780212402344
                  },
                  "absoluteRenderBounds": {
                    "x": -2853,
                    "y": 624.857177734375,
                    "width": 380,
                    "height": 501.8780517578125
                  },
                  "targetAspectRatio": {
                    "x": 546.6666870117188,
                    "y": 722
                  },
                  "constraints": {
                    "vertical": "TOP",
                    "horizontal": "LEFT"
                  },
                  "layoutAlign": "STRETCH",
                  "layoutGrow": 0,
                  "layoutSizingHorizontal": "FILL",
                  "layoutSizingVertical": "FIXED",
                  "effects": [],
                  "interactions": []
                },
                {
                  "id": "1:1342",
                  "name": "Image_2",
                  "type": "RECTANGLE",
                  "scrollBehavior": "SCROLLS",
                  "blendMode": "PASS_THROUGH",
                  "fills": [
                    {
                      "blendMode": "NORMAL",
                      "type": "IMAGE",
                      "scaleMode": "FILL",
                      "imageRef": "f2721c480945deaa65e894d34c41bf3f2a043474"
                    }
                  ],
                  "strokes": [],
                  "strokeWeight": 1,
                  "strokeAlign": "INSIDE",
                  "absoluteBoundingBox": {
                    "x": -2853,
                    "y": 1146.7352294921875,
                    "width": 380,
                    "height": 268.3170471191406
                  },
                  "absoluteRenderBounds": {
                    "x": -2853,
                    "y": 1146.7352294921875,
                    "width": 380,
                    "height": 268.3170166015625
                  },
                  "targetAspectRatio": {
                    "x": 546.6666870117188,
                    "y": 386
                  },
                  "constraints": {
                    "vertical": "TOP",
                    "horizontal": "LEFT"
                  },
                  "layoutAlign": "STRETCH",
                  "layoutGrow": 0,
                  "layoutSizingHorizontal": "FILL",
                  "layoutSizingVertical": "FIXED",
                  "effects": [],
                  "interactions": []
                },
                {
                  "id": "1:1344",
                  "name": "Image_3",
                  "type": "RECTANGLE",
                  "scrollBehavior": "SCROLLS",
                  "blendMode": "PASS_THROUGH",
                  "fills": [
                    {
                      "blendMode": "NORMAL",
                      "type": "IMAGE",
                      "scaleMode": "FILL",
                      "imageRef": "b03ea5eb2c7e55bdea68b03f298cc48d11d9b854"
                    }
                  ],
                  "strokes": [],
                  "strokeWeight": 1,
                  "strokeAlign": "INSIDE",
                  "absoluteBoundingBox": {
                    "x": -2853,
                    "y": 1435.05224609375,
                    "width": 380,
                    "height": 499.0975646972656
                  },
                  "absoluteRenderBounds": {
                    "x": -2853,
                    "y": 1435.05224609375,
                    "width": 380,
                    "height": 499.0975341796875
                  },
                  "targetAspectRatio": {
                    "x": 546.6666870117188,
                    "y": 718
                  },
                  "constraints": {
                    "vertical": "TOP",
                    "horizontal": "LEFT"
                  },
                  "layoutAlign": "STRETCH",
                  "layoutGrow": 0,
                  "layoutSizingHorizontal": "FILL",
                  "layoutSizingVertical": "FIXED",
                  "effects": [],
                  "interactions": []
                },
                {
                  "id": "1:1373",
                  "name": "Image_4",
                  "type": "RECTANGLE",
                  "scrollBehavior": "SCROLLS",
                  "blendMode": "PASS_THROUGH",
                  "fills": [
                    {
                      "blendMode": "NORMAL",
                      "type": "IMAGE",
                      "scaleMode": "FILL",
                      "imageRef": "d9bb51c777049924a9639ce1294cf8064d871aeb"
                    }
                  ],
                  "strokes": [],
                  "strokeWeight": 1,
                  "strokeAlign": "INSIDE",
                  "absoluteBoundingBox": {
                    "x": -2853,
                    "y": 1954.1497802734375,
                    "width": 380,
                    "height": 501.8780212402344
                  },
                  "absoluteRenderBounds": {
                    "x": -2853,
                    "y": 1954.1497802734375,
                    "width": 380,
                    "height": 501.8780517578125
                  },
                  "targetAspectRatio": {
                    "x": 546.6666870117188,
                    "y": 722
                  },
                  "constraints": {
                    "vertical": "TOP",
                    "horizontal": "LEFT"
                  },
                  "layoutAlign": "STRETCH",
                  "layoutGrow": 0,
                  "layoutSizingHorizontal": "FILL",
                  "layoutSizingVertical": "FIXED",
                  "effects": [],
                  "interactions": []
                },
                {
                  "id": "1:1345",
                  "name": "Image_6",
                  "type": "RECTANGLE",
                  "scrollBehavior": "SCROLLS",
                  "blendMode": "PASS_THROUGH",
                  "fills": [
                    {
                      "blendMode": "NORMAL",
                      "type": "IMAGE",
                      "scaleMode": "FILL",
                      "imageRef": "b949dd89bf892e0aca220eeb7137d4166456348c"
                    }
                  ],
                  "strokes": [],
                  "strokeWeight": 1,
                  "strokeAlign": "INSIDE",
                  "absoluteBoundingBox": {
                    "x": -2853,
                    "y": 2476.02783203125,
                    "width": 380,
                    "height": 499.0975646972656
                  },
                  "absoluteRenderBounds": {
                    "x": -2853,
                    "y": 2476.02783203125,
                    "width": 380,
                    "height": 499.09765625
                  },
                  "targetAspectRatio": {
                    "x": 546.6666870117188,
                    "y": 718
                  },
                  "constraints": {
                    "vertical": "TOP",
                    "horizontal": "LEFT"
                  },
                  "layoutAlign": "STRETCH",
                  "layoutGrow": 0,
                  "layoutSizingHorizontal": "FILL",
                  "layoutSizingVertical": "FIXED",
                  "effects": [],
                  "interactions": []
                }
              ],
              "blendMode": "PASS_THROUGH",
              "clipsContent": false,
              "background": [],
              "fills": [],
              "strokes": [],
              "strokeWeight": 1,
              "strokeAlign": "INSIDE",
              "backgroundColor": {
                "r": 0,
                "g": 0,
                "b": 0,
                "a": 0
              },
              "layoutMode": "VERTICAL",
              "counterAxisSizingMode": "FIXED",
              "itemSpacing": 20,
              "layoutWrap": "NO_WRAP",
              "absoluteBoundingBox": {
                "x": -2853,
                "y": 624.857177734375,
                "width": 380,
                "height": 2350.268310546875
              },
              "absoluteRenderBounds": {
                "x": -2853,
                "y": 624.857177734375,
                "width": 380,
                "height": 2350.268310546875
              },
              "constraints": {
                "vertical": "TOP",
                "horizontal": "LEFT"
              },
              "layoutAlign": "INHERIT",
              "layoutGrow": 1,
              "minWidth": 320,
              "maxWidth": 546,
              "layoutSizingHorizontal": "FILL",
              "layoutSizingVertical": "HUG",
              "effects": [],
              "interactions": []
            },
            {
              "id": "7:3134",
              "name": "Card",
              "type": "FRAME",
              "scrollBehavior": "SCROLLS",
              "boundVariables": {
                "minWidth": {
                  "type": "VARIABLE_ALIAS",
                  "id": "VariableID:131:4121"
                },
                "maxWidth": {
                  "type": "VARIABLE_ALIAS",
                  "id": "VariableID:131:4122"
                }
              },
              "children": [
                {
                  "id": "1:1350",
                  "name": "Image_7",
                  "type": "RECTANGLE",
                  "scrollBehavior": "SCROLLS",
                  "blendMode": "PASS_THROUGH",
                  "fills": [
                    {
                      "blendMode": "NORMAL",
                      "type": "IMAGE",
                      "scaleMode": "FILL",
                      "imageRef": "83256470affa99ab484c2a97fee3ecfc8918cf03"
                    }
                  ],
                  "strokes": [],
                  "strokeWeight": 1,
                  "strokeAlign": "INSIDE",
                  "absoluteBoundingBox": {
                    "x": -2453,
                    "y": 624.857177734375,
                    "width": 380,
                    "height": 349.6463623046875
                  },
                  "absoluteRenderBounds": {
                    "x": -2453,
                    "y": 624.857177734375,
                    "width": 380,
                    "height": 349.6463623046875
                  },
                  "targetAspectRatio": {
                    "x": 546.6666259765625,
                    "y": 503
                  },
                  "constraints": {
                    "vertical": "TOP",
                    "horizontal": "LEFT"
                  },
                  "layoutAlign": "STRETCH",
                  "layoutGrow": 0,
                  "layoutSizingHorizontal": "FILL",
                  "layoutSizingVertical": "FIXED",
                  "effects": [],
                  "interactions": []
                },
                {
                  "id": "1:1352",
                  "name": "Image_8",
                  "type": "RECTANGLE",
                  "scrollBehavior": "SCROLLS",
                  "blendMode": "PASS_THROUGH",
                  "fills": [
                    {
                      "blendMode": "NORMAL",
                      "type": "IMAGE",
                      "scaleMode": "FILL",
                      "imageRef": "9b33256c7995f80c6e08e44da932c2a80e6b1a92"
                    }
                  ],
                  "strokes": [],
                  "strokeWeight": 1,
                  "strokeAlign": "INSIDE",
                  "absoluteBoundingBox": {
                    "x": -2453,
                    "y": 994.5035400390625,
                    "width": 380,
                    "height": 420.5487976074219
                  },
                  "absoluteRenderBounds": {
                    "x": -2453,
                    "y": 994.5035400390625,
                    "width": 380,
                    "height": 420.548828125
                  },
                  "targetAspectRatio": {
                    "x": 546.6666259765625,
                    "y": 605
                  },
                  "constraints": {
                    "vertical": "TOP",
                    "horizontal": "LEFT"
                  },
                  "layoutAlign": "STRETCH",
                  "layoutGrow": 0,
                  "layoutSizingHorizontal": "FILL",
                  "layoutSizingVertical": "FIXED",
                  "effects": [],
                  "interactions": []
                },
                {
                  "id": "1:1354",
                  "name": "Image_9",
                  "type": "RECTANGLE",
                  "scrollBehavior": "SCROLLS",
                  "blendMode": "PASS_THROUGH",
                  "fills": [
                    {
                      "blendMode": "NORMAL",
                      "type": "IMAGE",
                      "scaleMode": "FILL",
                      "imageRef": "bda0046e0360dbc618f40198d100974d1c4f58b0"
                    }
                  ],
                  "strokes": [],
                  "strokeWeight": 1,
                  "strokeAlign": "INSIDE",
                  "absoluteBoundingBox": {
                    "x": -2453,
                    "y": 1435.0523681640625,
                    "width": 380,
                    "height": 499.0976257324219
                  },
                  "absoluteRenderBounds": {
                    "x": -2453,
                    "y": 1435.0523681640625,
                    "width": 380,
                    "height": 499.09765625
                  },
                  "targetAspectRatio": {
                    "x": 546.6666259765625,
                    "y": 718
                  },
                  "constraints": {
                    "vertical": "TOP",
                    "horizontal": "LEFT"
                  },
                  "layoutAlign": "STRETCH",
                  "layoutGrow": 0,
                  "layoutSizingHorizontal": "FILL",
                  "layoutSizingVertical": "FIXED",
                  "effects": [],
                  "interactions": []
                },
                {
                  "id": "1:1353",
                  "name": "Image_10",
                  "type": "RECTANGLE",
                  "scrollBehavior": "SCROLLS",
                  "blendMode": "PASS_THROUGH",
                  "fills": [
                    {
                      "blendMode": "NORMAL",
                      "type": "IMAGE",
                      "scaleMode": "FILL",
                      "imageRef": "f9cf1434a484cd576d6f971b9d04884e33fb0f6c"
                    }
                  ],
                  "strokes": [],
                  "strokeWeight": 1,
                  "strokeAlign": "INSIDE",
                  "absoluteBoundingBox": {
                    "x": -2453,
                    "y": 1954.1500244140625,
                    "width": 380,
                    "height": 420.5487976074219
                  },
                  "absoluteRenderBounds": {
                    "x": -2453,
                    "y": 1954.1500244140625,
                    "width": 380,
                    "height": 420.5487060546875
                  },
                  "targetAspectRatio": {
                    "x": 546.6666259765625,
                    "y": 605
                  },
                  "constraints": {
                    "vertical": "TOP",
                    "horizontal": "LEFT"
                  },
                  "layoutAlign": "STRETCH",
                  "layoutGrow": 0,
                  "layoutSizingHorizontal": "FILL",
                  "layoutSizingVertical": "FIXED",
                  "effects": [],
                  "interactions": []
                },
                {
                  "id": "1:1355",
                  "name": "Image_11",
                  "type": "RECTANGLE",
                  "scrollBehavior": "SCROLLS",
                  "blendMode": "PASS_THROUGH",
                  "fills": [
                    {
                      "blendMode": "NORMAL",
                      "type": "IMAGE",
                      "scaleMode": "FILL",
                      "imageRef": "c24498300479f5cc3298e52728735b3f5838ccbe"
                    }
                  ],
                  "strokes": [],
                  "strokeWeight": 1,
                  "strokeAlign": "INSIDE",
                  "absoluteBoundingBox": {
                    "x": -2453,
                    "y": 2394.69873046875,
                    "width": 380,
                    "height": 499.0976257324219
                  },
                  "absoluteRenderBounds": {
                    "x": -2453,
                    "y": 2394.69873046875,
                    "width": 380,
                    "height": 499.09765625
                  },
                  "targetAspectRatio": {
                    "x": 546.6666259765625,
                    "y": 718
                  },
                  "constraints": {
                    "vertical": "TOP",
                    "horizontal": "LEFT"
                  },
                  "layoutAlign": "STRETCH",
                  "layoutGrow": 0,
                  "layoutSizingHorizontal": "FILL",
                  "layoutSizingVertical": "FIXED",
                  "effects": [],
                  "interactions": []
                }
              ],
              "blendMode": "PASS_THROUGH",
              "clipsContent": false,
              "background": [],
              "fills": [],
              "strokes": [],
              "strokeWeight": 1,
              "strokeAlign": "INSIDE",
              "backgroundColor": {
                "r": 0,
                "g": 0,
                "b": 0,
                "a": 0
              },
              "layoutMode": "VERTICAL",
              "counterAxisSizingMode": "FIXED",
              "itemSpacing": 20,
              "layoutWrap": "NO_WRAP",
              "absoluteBoundingBox": {
                "x": -2453,
                "y": 624.857177734375,
                "width": 380,
                "height": 2268.939208984375
              },
              "absoluteRenderBounds": {
                "x": -2453,
                "y": 624.857177734375,
                "width": 380,
                "height": 2268.939208984375
              },
              "constraints": {
                "vertical": "TOP",
                "horizontal": "LEFT"
              },
              "layoutAlign": "INHERIT",
              "layoutGrow": 1,
              "minWidth": 320,
              "maxWidth": 546,
              "layoutSizingHorizontal": "FILL",
              "layoutSizingVertical": "HUG",
              "effects": [],
              "interactions": []
            },
            {
              "id": "7:3133",
              "name": "Card",
              "type": "FRAME",
              "scrollBehavior": "SCROLLS",
              "boundVariables": {
                "minWidth": {
                  "type": "VARIABLE_ALIAS",
                  "id": "VariableID:131:4121"
                },
                "maxWidth": {
                  "type": "VARIABLE_ALIAS",
                  "id": "VariableID:131:4122"
                }
              },
              "children": [
                {
                  "id": "1:1356",
                  "name": "Image_100",
                  "type": "RECTANGLE",
                  "scrollBehavior": "SCROLLS",
                  "blendMode": "PASS_THROUGH",
                  "fills": [
                    {
                      "blendMode": "NORMAL",
                      "type": "IMAGE",
                      "scaleMode": "FILL",
                      "imageRef": "fb3defd08af108479c3faf48574ef632a2e6e0f6"
                    }
                  ],
                  "strokes": [],
                  "strokeWeight": 1,
                  "strokeAlign": "INSIDE",
                  "absoluteBoundingBox": {
                    "x": -2053,
                    "y": 624.857177734375,
                    "width": 380,
                    "height": 501.87811279296875
                  },
                  "absoluteRenderBounds": {
                    "x": -2053,
                    "y": 624.857177734375,
                    "width": 380,
                    "height": 501.878173828125
                  },
                  "targetAspectRatio": {
                    "x": 546.6666259765625,
                    "y": 722
                  },
                  "constraints": {
                    "vertical": "TOP",
                    "horizontal": "LEFT"
                  },
                  "layoutAlign": "STRETCH",
                  "layoutGrow": 0,
                  "layoutSizingHorizontal": "FILL",
                  "layoutSizingVertical": "FIXED",
                  "effects": [],
                  "interactions": []
                },
                {
                  "id": "1:1346",
                  "name": "Image_99",
                  "type": "RECTANGLE",
                  "scrollBehavior": "SCROLLS",
                  "blendMode": "PASS_THROUGH",
                  "fills": [
                    {
                      "blendMode": "NORMAL",
                      "type": "IMAGE",
                      "scaleMode": "FILL",
                      "imageRef": "70ee3a5f178bfc6ca21fca6d79b2fbb3267f62db"
                    }
                  ],
                  "strokes": [],
                  "strokeWeight": 1,
                  "strokeAlign": "INSIDE",
                  "absoluteBoundingBox": {
                    "x": -2053,
                    "y": 1146.7353515625,
                    "width": 380,
                    "height": 513.0000610351562
                  },
                  "absoluteRenderBounds": {
                    "x": -2053,
                    "y": 1146.7353515625,
                    "width": 380,
                    "height": 513
                  },
                  "targetAspectRatio": {
                    "x": 546.6666259765625,
                    "y": 738
                  },
                  "constraints": {
                    "vertical": "TOP",
                    "horizontal": "LEFT"
                  },
                  "layoutAlign": "STRETCH",
                  "layoutGrow": 0,
                  "layoutSizingHorizontal": "FILL",
                  "layoutSizingVertical": "FIXED",
                  "effects": [],
                  "interactions": []
                },
                {
                  "id": "1:1348",
                  "name": "Image",
                  "type": "RECTANGLE",
                  "scrollBehavior": "SCROLLS",
                  "blendMode": "PASS_THROUGH",
                  "fills": [
                    {
                      "blendMode": "NORMAL",
                      "type": "IMAGE",
                      "scaleMode": "FILL",
                      "imageRef": "f2721c480945deaa65e894d34c41bf3f2a043474"
                    }
                  ],
                  "strokes": [],
                  "strokeWeight": 1,
                  "strokeAlign": "INSIDE",
                  "absoluteBoundingBox": {
                    "x": -2053,
                    "y": 1679.7353515625,
                    "width": 380,
                    "height": 254.4146270751953
                  },
                  "absoluteRenderBounds": {
                    "x": -2053,
                    "y": 1679.7353515625,
                    "width": 380,
                    "height": 254.4146728515625
                  },
                  "targetAspectRatio": {
                    "x": 546.6666259765625,
                    "y": 366
                  },
                  "constraints": {
                    "vertical": "TOP",
                    "horizontal": "LEFT"
                  },
                  "layoutAlign": "STRETCH",
                  "layoutGrow": 0,
                  "layoutSizingHorizontal": "FILL",
                  "layoutSizingVertical": "FIXED",
                  "effects": [],
                  "interactions": []
                },
                {
                  "id": "1:1357",
                  "name": "Image_98",
                  "type": "RECTANGLE",
                  "scrollBehavior": "SCROLLS",
                  "blendMode": "PASS_THROUGH",
                  "fills": [
                    {
                      "blendMode": "NORMAL",
                      "type": "IMAGE",
                      "scaleMode": "FILL",
                      "imageRef": "22e399db2ce3424c93ff7d5f506d674d3afef871"
                    }
                  ],
                  "strokes": [],
                  "strokeWeight": 1,
                  "strokeAlign": "INSIDE",
                  "absoluteBoundingBox": {
                    "x": -2053,
                    "y": 1954.14990234375,
                    "width": 380,
                    "height": 501.87811279296875
                  },
                  "absoluteRenderBounds": {
                    "x": -2053,
                    "y": 1954.14990234375,
                    "width": 380,
                    "height": 501.878173828125
                  },
                  "targetAspectRatio": {
                    "x": 546.6666259765625,
                    "y": 722
                  },
                  "constraints": {
                    "vertical": "TOP",
                    "horizontal": "LEFT"
                  },
                  "layoutAlign": "STRETCH",
                  "layoutGrow": 0,
                  "layoutSizingHorizontal": "FILL",
                  "layoutSizingVertical": "FIXED",
                  "effects": [],
                  "interactions": []
                },
                {
                  "id": "1:1347",
                  "name": "Image_97",
                  "type": "RECTANGLE",
                  "scrollBehavior": "SCROLLS",
                  "blendMode": "PASS_THROUGH",
                  "fills": [
                    {
                      "blendMode": "NORMAL",
                      "type": "IMAGE",
                      "scaleMode": "FILL",
                      "imageRef": "aaf827ce25d16c5dbf4c8677042631aaeb0e738d"
                    }
                  ],
                  "strokes": [],
                  "strokeWeight": 1,
                  "strokeAlign": "INSIDE",
                  "absoluteBoundingBox": {
                    "x": -2053,
                    "y": 2476.028076171875,
                    "width": 380,
                    "height": 513.0000610351562
                  },
                  "absoluteRenderBounds": {
                    "x": -2053,
                    "y": 2476.028076171875,
                    "width": 380,
                    "height": 513
                  },
                  "targetAspectRatio": {
                    "x": 546.6666259765625,
                    "y": 738
                  },
                  "constraints": {
                    "vertical": "TOP",
                    "horizontal": "LEFT"
                  },
                  "layoutAlign": "STRETCH",
                  "layoutGrow": 0,
                  "layoutSizingHorizontal": "FILL",
                  "layoutSizingVertical": "FIXED",
                  "effects": [],
                  "interactions": []
                },
                {
                  "id": "1:1349",
                  "name": "Image_96",
                  "type": "RECTANGLE",
                  "scrollBehavior": "SCROLLS",
                  "blendMode": "PASS_THROUGH",
                  "fills": [
                    {
                      "blendMode": "NORMAL",
                      "type": "IMAGE",
                      "scaleMode": "FILL",
                      "imageRef": "40de5a99a19f533d07ea60533a660fea5febf2f7"
                    }
                  ],
                  "strokes": [],
                  "strokeWeight": 1,
                  "strokeAlign": "INSIDE",
                  "absoluteBoundingBox": {
                    "x": -2053,
                    "y": 3009.028076171875,
                    "width": 380,
                    "height": 254.4146270751953
                  },
                  "absoluteRenderBounds": {
                    "x": -2053,
                    "y": 3009.028076171875,
                    "width": 380,
                    "height": 254.41455078125
                  },
                  "targetAspectRatio": {
                    "x": 546.6666259765625,
                    "y": 366
                  },
                  "constraints": {
                    "vertical": "TOP",
                    "horizontal": "LEFT"
                  },
                  "layoutAlign": "STRETCH",
                  "layoutGrow": 0,
                  "layoutSizingHorizontal": "FILL",
                  "layoutSizingVertical": "FIXED",
                  "effects": [],
                  "interactions": []
                }
              ],
              "blendMode": "PASS_THROUGH",
              "clipsContent": false,
              "background": [],
              "fills": [],
              "strokes": [],
              "strokeWeight": 1,
              "strokeAlign": "INSIDE",
              "backgroundColor": {
                "r": 0,
                "g": 0,
                "b": 0,
                "a": 0
              },
              "layoutMode": "VERTICAL",
              "counterAxisSizingMode": "FIXED",
              "itemSpacing": 20,
              "layoutWrap": "NO_WRAP",
              "absoluteBoundingBox": {
                "x": -2053,
                "y": 624.857177734375,
                "width": 380,
                "height": 2638.585693359375
              },
              "absoluteRenderBounds": {
                "x": -2053,
                "y": 624.857177734375,
                "width": 380,
                "height": 2638.585662841797
              },
              "constraints": {
                "vertical": "TOP",
                "horizontal": "LEFT"
              },
              "layoutAlign": "INHERIT",
              "layoutGrow": 1,
              "minWidth": 320,
              "maxWidth": 546,
              "layoutSizingHorizontal": "FILL",
              "layoutSizingVertical": "HUG",
              "effects": [],
              "interactions": []
            }
          ],
          "blendMode": "PASS_THROUGH",
          "clipsContent": false,
          "background": [],
          "fills": [],
          "strokes": [],
          "strokeWeight": 1,
          "strokeAlign": "INSIDE",
          "backgroundColor": {
            "r": 0,
            "g": 0,
            "b": 0,
            "a": 0
          },
          "layoutMode": "HORIZONTAL",
          "primaryAxisSizingMode": "FIXED",
          "itemSpacing": 20,
          "layoutWrap": "WRAP",
          "counterAxisSpacing": 20,
          "counterAxisAlignContent": "AUTO",
          "absoluteBoundingBox": {
            "x": -2853,
            "y": 624.857177734375,
            "width": 1180,
            "height": 2638.585693359375
          },
          "absoluteRenderBounds": {
            "x": -2853,
            "y": 624.857177734375,
            "width": 1180,
            "height": 2638.585662841797
          },
          "constraints": {
            "vertical": "TOP",
            "horizontal": "LEFT"
          },
          "layoutAlign": "STRETCH",
          "layoutGrow": 0,
          "layoutSizingHorizontal": "FILL",
          "layoutSizingVertical": "HUG",
          "effects": [],
          "interactions": []
        }
      ],
      "blendMode": "PASS_THROUGH",
      "clipsContent": false,
      "background": [],
      "fills": [],
      "strokes": [],
      "strokeWeight": 1,
      "strokeAlign": "INSIDE",
      "backgroundColor": {
        "r": 0,
        "g": 0,
        "b": 0,
        "a": 0
      },
      "layoutMode": "VERTICAL",
      "counterAxisSizingMode": "FIXED",
      "primaryAxisAlignItems": "CENTER",
      "itemSpacing": 10,
      "layoutWrap": "NO_WRAP",
      "absoluteBoundingBox": {
        "x": -2853,
        "y": 624.857177734375,
        "width": 1180,
        "height": 2638.585693359375
      },
      "absoluteRenderBounds": {
        "x": -2853,
        "y": 624.857177734375,
        "width": 1180,
        "height": 2638.585662841797
      },
      "constraints": {
        "vertical": "TOP",
        "horizontal": "LEFT"
      },
      "layoutAlign": "STRETCH",
      "layoutGrow": 0,
      "layoutSizingHorizontal": "FILL",
      "layoutSizingVertical": "HUG",
      "effects": [],
      "interactions": []
    }
  ],
  "blendMode": "PASS_THROUGH",
  "clipsContent": true,
  "background": [],
  "fills": [],
  "strokes": [],
  "strokeWeight": 1,
  "strokeAlign": "INSIDE",
  "backgroundColor": {
    "r": 0,
    "g": 0,
    "b": 0,
    "a": 0
  },
  "layoutMode": "VERTICAL",
  "counterAxisSizingMode": "FIXED",
  "counterAxisAlignItems": "CENTER",
  "itemSpacing": 48,
  "layoutWrap": "NO_WRAP",
  "absoluteBoundingBox": {
    "x": -2853,
    "y": 390.8571472167969,
    "width": 1180,
    "height": 2872.585693359375
  },
  "absoluteRenderBounds": {
    "x": -2853,
    "y": 390.8571472167969,
    "width": 1180,
    "height": 2872.585693359375
  },
  "constraints": {
    "vertical": "TOP",
    "horizontal": "LEFT"
  },
  "layoutAlign": "STRETCH",
  "layoutGrow": 0,
  "layoutSizingHorizontal": "FILL",
  "layoutSizingVertical": "HUG",
  "effects": [],
  "interactions": []
}